populisengineagentsmanagementdb/__init__.py
populisengineagentsmanagementdb/config.py
populisengineagentsmanagementdb/crud.py
populisengineagentsmanagementdb/database.py
populisengineagentsmanagementdb/exceptions.py
populisengineagentsmanagementdb/models.py
populisengineagentsmanagementdb-0.1.12.dist-info/METADATA
populisengineagentsmanagementdb-0.1.12.dist-info/WHEEL
populisengineagentsmanagementdb-0.1.12.dist-info/top_level.txt
populisengineagentsmanagementdb-0.1.12.dist-info/RECORD
