Metadata-Version: 2.1
Name: populisengineagentsmanagementdb
Version: 0.1.12
Summary: Management CRUD in MongoDB
Author-email: Grenne <grenne@populisrh.com>
Classifier: Programming Language :: Python :: 3
Classifier: License :: OSI Approved :: MIT License
Classifier: Operating System :: OS Independent
Requires-Python: >=3.6
Requires-Dist: pymongo
